django_pg_commands/__init__.py
django_pg_commands/tests.py
django_pg_commands/utils.py
django_pg_commands/management/__init__.py
django_pg_commands/management/commands/__init__.py
django_pg_commands/management/commands/syncfunctions.py
django_pg_commands-0.1.3.dist-info/DESCRIPTION.rst
django_pg_commands-0.1.3.dist-info/LICENSE.txt
django_pg_commands-0.1.3.dist-info/METADATA
django_pg_commands-0.1.3.dist-info/RECORD
django_pg_commands-0.1.3.dist-info/WHEEL
django_pg_commands-0.1.3.dist-info/metadata.json
django_pg_commands-0.1.3.dist-info/top_level.txt
tests/__init__.py
tests/run.py
tests/run_test.py
