Metadata-Version: 2.0
Name: django-pg-commands
Version: 0.1.3
Summary: Collections of command for postgreSQL with django
Home-page: http://github.com/franzemil/django_pg_commands
Author: Franz Emil Eulate Chacolla
Author-email: franzemil35@gmail.com
License: MIT
Keywords: postgreSQL,django
Platform: UNKNOWN
Requires-Dist: inquirer
Requires-Dist: psycopg2
